progimagemodels/__init__.py
progimagemodels/client.py
progimagemodels/image.py
progimagemodels-0.1.2.dist-info/LICENCE
progimagemodels-0.1.2.dist-info/METADATA
progimagemodels-0.1.2.dist-info/WHEEL
progimagemodels-0.1.2.dist-info/top_level.txt
progimagemodels-0.1.2.dist-info/RECORD
