Metadata-Version: 2.1
Name: progimagemodels
Version: 0.1.2
Summary: Python models for the ProgImage API
Home-page: UNKNOWN
Author: Nasko Grozdanov
Author-email: antonasko@gmail.com
License: UNKNOWN
Platform: UNKNOWN
Classifier: Programming Language :: Python :: 3
Classifier: License :: OSI Approved :: MIT License
Classifier: Operating System :: OS Independent
Requires-Dist: Pillow (==6.0.0)
Requires-Dist: pytest (==4.4.0)
